WinPos/__init__.py
WinPos/win_pos.py
win_pos-0.1.0.dist-info/METADATA
win_pos-0.1.0.dist-info/WHEEL
win_pos-0.1.0.dist-info/top_level.txt
win_pos-0.1.0.dist-info/RECORD
