Metadata-Version: 2.1
Name: win-pos
Version: 0.1.0
Summary: Add utility methods that allow you to easily grab the position of a window
Home-page: https://github.com/liam-edwards/python-window-positions
Author: Liam Edwards
Author-email: me@liamedwards.dev
License: LICENSE.txt
Project-URL: Documentation, https://github.com/liam-edwards/python-window-positions
Project-URL: Source, https://github.com/liam-edwards/python-window-positions
Project-URL: Tracker, https://github.com/liam-edwards/python-window-positions/issues
Keywords: windows,window,position,helpers,human friendly,python
Classifier: Development Status :: 5 - Production/Stable
Classifier: Intended Audience :: Developers
Classifier: Programming Language :: Python :: 3.7
Classifier: Programming Language :: Python :: 3.8
Classifier: Programming Language :: Python :: 3.9
Classifier: Programming Language :: Python :: 3.10
Classifier: Programming Language :: Python :: 3.11
Classifier: Programming Language :: Python :: 3.12
Classifier: Programming Language :: Python :: 3 :: Only
Classifier: License :: OSI Approved :: MIT License
Classifier: Operating System :: Microsoft :: Windows
Classifier: Typing :: Typed
Requires-Python: >=3.7
Requires-Dist: pywin32
